g_mlp_pytorch/__init__.py
g_mlp_pytorch/autoregressive_wrapper.py
g_mlp_pytorch/g_mlp_pytorch.py
g_mlp_pytorch-0.1.5.dist-info/LICENSE
g_mlp_pytorch-0.1.5.dist-info/METADATA
g_mlp_pytorch-0.1.5.dist-info/WHEEL
g_mlp_pytorch-0.1.5.dist-info/top_level.txt
g_mlp_pytorch-0.1.5.dist-info/RECORD
