Metadata-Version: 2.1
Name: g-mlp-pytorch
Version: 0.1.5
Summary: gMLP - Pytorch
Home-page: https://github.com/lucidrains/g-mlp-pytorch
Author: Phil Wang
Author-email: lucidrains@gmail.com
License: MIT
Keywords: artificial intelligence,deep learning,multi-layered-preceptrons
Platform: UNKNOWN
Classifier: Development Status :: 4 - Beta
Classifier: Intended Audience :: Developers
Classifier: Topic :: Scientific/Engineering :: Artificial Intelligence
Classifier: License :: OSI Approved :: MIT License
Classifier: Programming Language :: Python :: 3.6
Requires-Dist: einops (>=0.3)
Requires-Dist: torch (>=1.6)
